browser_core/__init__.py
browser_core/cli.py
browser_core/exceptions.py
browser_core/logging.py
browser_core/settings.py
browser_core/types.py
browser_core/utils.py
browser_core/drivers/__init__.py
browser_core/drivers/manager.py
browser_core/engines/__init__.py
browser_core/engines/base.py
browser_core/engines/playwright_engine.py
browser_core/engines/selenium/__init__.py
browser_core/engines/selenium/base_engine.py
browser_core/engines/selenium/chrome.py
browser_core/engines/selenium/firefox.py
browser_core/engines/selenium/provider.py
browser_core/orchestration/__init__.py
browser_core/orchestration/factory.py
browser_core/orchestration/manager.py
browser_core/orchestration/worker.py
browser_core/selectors/__init__.py
browser_core/selectors/element_proxy.py
browser_core/selectors/manager.py
browser_core/selectors/multi_proxy.py
browser_core/snapshots/__init__.py
browser_core/snapshots/manager.py
browser_core/storage/__init__.py
browser_core/storage/engine.py
browser_core/windows/__init__.py
browser_core/windows/manager.py
browser_core/windows/tab.py
browser_core-2.7.0.dist-info/licenses/LICENSE
browser_core-2.7.0.dist-info/METADATA
browser_core-2.7.0.dist-info/WHEEL
browser_core-2.7.0.dist-info/entry_points.txt
browser_core-2.7.0.dist-info/top_level.txt
browser_core-2.7.0.dist-info/RECORD
