Metadata-Version: 2.4
Name: browser-core
Version: 2.7.0
Summary: Um framework robusto e configurável para automação de navegadores, com gestão de perfis, sessões e uma CLI.
Author: gabigolo
License: MIT
Project-URL: Homepage, https://github.com/gabrielbarbosel/browser-core
Project-URL: Bug Tracker, https://github.com/gabrielbarbosel/browser-core/issues
Project-URL: Repository, https://github.com/gabrielbarbosel/browser-core
Keywords: automation,selenium,web,browser,framework
Classifier: Development Status :: 5 - Production/Stable
Classifier: Intended Audience :: Developers
Classifier: License :: OSI Approved :: MIT License
Classifier: Programming Language :: Python :: 3
Classifier: Programming Language :: Python :: 3.8
Classifier: Programming Language :: Python :: 3.9
Classifier: Programming Language :: Python :: 3.10
Classifier: Programming Language :: Python :: 3.11
Classifier: Topic :: Software Development :: Libraries :: Python Modules
Classifier: Topic :: Software Development :: Testing
Requires-Python: >=3.8
License-File: LICENSE
Requires-Dist: selenium>=4.15.0
Requires-Dist: webdriver-manager>=4.0.1
Requires-Dist: click>=8.0.0
Requires-Dist: typing-extensions>=4.0.0
Requires-Dist: playwright>=1.30.0
Requires-Dist: psutil>=5.9.0
Dynamic: license-file
